stratum/__init__.py
stratum/connection_registry.py
stratum/event_handler.py
stratum/exceptions.py
stratum/http_transport.py
stratum/protocol.py
stratum/pubsub.py
stratum/semaphore.py
stratum/services.py
stratum/signature.py
stratum/stats.py
stratum/version.py
tests/__init__.py
tests/test_version.py
stratum_core-0.0.2.dist-info/METADATA
stratum_core-0.0.2.dist-info/WHEEL
stratum_core-0.0.2.dist-info/top_level.txt
stratum_core-0.0.2.dist-info/RECORD
