Metadata-Version: 2.1
Name: stratum-core
Version: 0.0.2
Summary: Stratum server implementation based on Twisted
Home-page: https://github.com/Kryptos-Team/stratum-core.git
Author: Abhimanyu Saharan
Author-email: desk.abhimanyu@gmail.com
License: MIT
Keywords: stratum,mining,kryptos
Platform: UNKNOWN
Classifier: Development Status :: 3 - Alpha
Classifier: Environment :: Console
Classifier: Environment :: No Input/Output (Daemon)
Classifier: Framework :: Pytest
Classifier: Intended Audience :: Developers
Classifier: Intended Audience :: Education
Classifier: Intended Audience :: Financial and Insurance Industry
Classifier: Intended Audience :: Information Technology
Classifier: License :: OSI Approved :: MIT License
Classifier: Natural Language :: English
Classifier: Operating System :: Unix
Classifier: Programming Language :: Python :: 3.7
Classifier: Programming Language :: Python :: 3.8
Classifier: Programming Language :: Python :: 3.9
Classifier: Topic :: Education
Classifier: Topic :: Utilities
Requires-Dist: logzero
Requires-Dist: setuptools
Requires-Dist: twisted
